amazon/__init__.py
amazon/api.py
amazon/metadata.py
python_amazon_unthrottled_paapi-0.1.1.dist-info/LICENSE
python_amazon_unthrottled_paapi-0.1.1.dist-info/METADATA
python_amazon_unthrottled_paapi-0.1.1.dist-info/WHEEL
python_amazon_unthrottled_paapi-0.1.1.dist-info/top_level.txt
python_amazon_unthrottled_paapi-0.1.1.dist-info/RECORD
