Metadata-Version: 2.1
Name: python-amazon-unthrottled-paapi
Version: 0.1.1
Summary: Amazon Unthrottled Access to Amazon Product Advertising API for Python
Home-page: https://github.com/nhapentor/python-amazon-unthrottled-paapi
Author: Samphan Pojanasophanakul
Author-email: nhapentor@gmail.com
License: MIT
Keywords: amazon,product advertising,paapi,api
Platform: UNKNOWN
Classifier: Programming Language :: Python :: 3
Classifier: License :: OSI Approved :: MIT License
Classifier: Operating System :: OS Independent
